{
	"storyname": "Famous Missing Treasures",
	"pages": [
		{
			"pagefile": "./stories/missingtreasures/page1.html",
			"correctcards": [],
			"answerordermatters": 0,
			"answerfile": "none"
		},
		{
			"pagefile": "./stories/missingtreasures/page2.html",
			"correctcards": ["amberroom"],
			"answerordermatters": 0,
			"answerfile": "./stories/missingtreasures/page2_answer.html"
		},
		{
			"pagefile": "./stories/missingtreasures/page3.html",
			"correctcards": ["arkofthecovenant"],
			"answerordermatters": 0,
			"answerfile": "./stories/missingtreasures/page3_answer.html"
		},
		{
			"pagefile": "./stories/missingtreasures/page4.html",
			"correctcards": ["hernandocortes","montezumaii","laketexcoco"],
			"answerordermatters": 1,
			"answerfile": "./stories/missingtreasures/page4_answer.html"
		}
	]
}
